filtered_faiss_lookup_pkg/__init__.py
filtered_faiss_lookup_pkg/tools/__init__.py
filtered_faiss_lookup_pkg/tools/filtered_faiss_lookup_tool.py
filtered_faiss_lookup_pkg/tools/utils.py
filtered_faiss_lookup_pkg/yamls/filtered_faiss_lookup_tool.yaml
my_tool_package/__init__.py
my_tool_package/tools/__init__.py
my_tool_package/tools/custom_lookup_tool.py
my_tool_package/tools/my_tool_1.py
my_tool_package/tools/my_tool_2.py
my_tool_package/tools/tool_with_cascading_inputs.py
my_tool_package/tools/tool_with_custom_llm_type.py
my_tool_package/tools/tool_with_custom_strong_type_connection.py
my_tool_package/tools/tool_with_dynamic_list_input.py
my_tool_package/tools/tool_with_file_path_input.py
my_tool_package/tools/tool_with_generated_by_input.py
my_tool_package/tools/utils.py
my_tool_package/yamls/custom_lookup_tool.yaml
my_tool_package/yamls/my_tool_1.yaml
my_tool_package/yamls/my_tool_2.yaml
my_tool_package/yamls/tool_with_cascading_inputs.yaml
my_tool_package/yamls/tool_with_custom_llm_type.yaml
my_tool_package/yamls/tool_with_custom_strong_type_connection.yaml
my_tool_package/yamls/tool_with_dynamic_list_input.yaml
my_tool_package/yamls/tool_with_file_path_input.yaml
my_tool_package/yamls/tool_with_generated_by_input.yaml
tests/__init__.py
tests/test_my_tool_1.py
tests/test_my_tool_2.py
tests/test_tool_with_cascading_inputs.py
tests/test_tool_with_custom_llm_type.py
tests/test_tool_with_custom_strong_type_connection.py
tests/test_tool_with_dynamic_input.py
tests/test_tool_with_file_path_input.py
tests/test_tool_with_generated_by_input.py
ilionx_filtered_faiss_lookup_pkg-0.0.1.dist-info/METADATA
ilionx_filtered_faiss_lookup_pkg-0.0.1.dist-info/WHEEL
ilionx_filtered_faiss_lookup_pkg-0.0.1.dist-info/entry_points.txt
ilionx_filtered_faiss_lookup_pkg-0.0.1.dist-info/top_level.txt
ilionx_filtered_faiss_lookup_pkg-0.0.1.dist-info/RECORD
