Metadata-Version: 2.1
Name: ilionx-filtered-faiss-lookup-pkg
Version: 0.0.1
Summary: Tool package to download a FAISS index from an Azure blobstore, do a similarity search and retrieve answers which can be filtered on metadata.
Provides-Extra: azure
Requires-Dist: azure-ai-ml <2.0.0,>=1.11.0 ; extra == 'azure'
